HISTORY.rst
LICENSE
MANIFEST.in
README.rst
setup.cfg
setup.py
libre/__init__.py
libre/requirements.txt
libre/settings.py
libre/urls.py
libre/wsgi.py
libre.egg-info/PKG-INFO
libre.egg-info/SOURCES.txt
libre.egg-info/dependency_links.txt
libre.egg-info/not-zip-safe
libre.egg-info/requires.txt
libre.egg-info/top_level.txt
libre/apps/__init__.py
libre/apps/data_drivers/__init__.py
libre/apps/data_drivers/actions.py
libre/apps/data_drivers/admin.py
libre/apps/data_drivers/aggregates.py
libre/apps/data_drivers/authentication.py
libre/apps/data_drivers/encoders.py
libre/apps/data_drivers/exceptions.py
libre/apps/data_drivers/filters.py
libre/apps/data_drivers/forms.py
libre/apps/data_drivers/job_processing.py
libre/apps/data_drivers/literals.py
libre/apps/data_drivers/managers.py
libre/apps/data_drivers/models.py
libre/apps/data_drivers/permissions.py
libre/apps/data_drivers/query.py
libre/apps/data_drivers/renderers.py
libre/apps/data_drivers/response.py
libre/apps/data_drivers/schedules.py
libre/apps/data_drivers/serializers.py
libre/apps/data_drivers/settings.py
libre/apps/data_drivers/tests.py
libre/apps/data_drivers/urls.py
libre/apps/data_drivers/utils.py
libre/apps/data_drivers/views.py
libre/apps/data_drivers/migrations/0001_initial.py
libre/apps/data_drivers/migrations/0002_auto__add_field_sourceshape_new_projection.py
libre/apps/data_drivers/migrations/0003_auto__add_shapefilecolumn.py
libre/apps/data_drivers/migrations/0004_auto__add_field_shapefilecolumn_data_type.py
libre/apps/data_drivers/migrations/0005_auto__add_field_source_published.py
libre/apps/data_drivers/migrations/0006_auto__add_field_spreadsheetcolumn_skip_regex__add_field_spreadsheetcol.py
libre/apps/data_drivers/migrations/0007_auto__add_sourcedatabase.py
libre/apps/data_drivers/migrations/0008_auto__add_databaseresultcolumn.py
libre/apps/data_drivers/migrations/0009_auto__add_field_sourcedatabase_limit.py
libre/apps/data_drivers/migrations/0010_auto__add_field_csvcolumn_skip_regex__add_field_csvcolumn_import_regex.py
libre/apps/data_drivers/migrations/0011_auto__add_field_shapefilecolumn_new_name.py
