Metadata-Version: 1.1
Name: libre
Version: 1.2
Summary: A Python based open data API engine.
Home-page: https://github.com/commonwealth-of-puerto-rico/libre
Author: Roberto Rosario
Author-email: rrosario@ogp.pr.gov
License:                     GNU GENERAL PUBLIC LICENSE
